Metadata-Version: 1.1
Name: uwsgi-cloudwatch
Version: 0.0.1.2
Summary: uwsgi-cloudwatch
Home-page: https://github.com/wdtinc/uwsgi-cloudwatch
Author: Justin Stewart
Author-email: jstewart@wdtinc.com
License: UNKNOWN
Platform: UNKNOWN
Classifier: Development Status :: 3 - Alpha
Classifier: Intended Audience :: Developers
Classifier: Natural Language :: English
Classifier: Programming Language :: Python
Classifier: Programming Language :: Python :: 3.5
